aiosyslogd/__init__.py
aiosyslogd/auth.py
aiosyslogd/config.py
aiosyslogd/db/__init__.py
aiosyslogd/db/logs_utils.py
aiosyslogd/db/meilisearch.py
aiosyslogd/db/sqlite.py
aiosyslogd/db/sqlite_utils.py
aiosyslogd/priority.py
aiosyslogd/rfc5424.py
aiosyslogd/server.py
aiosyslogd/templates/base.html
aiosyslogd/templates/index.html
aiosyslogd/templates/index.html.orig
aiosyslogd/templates/login.html
aiosyslogd/templates/profile.html
aiosyslogd/templates/user_form.html
aiosyslogd/templates/users.html
aiosyslogd/web.py
aiosyslogd/web.py.orig
aiosyslogd-1.1.0.dist-info/METADATA
aiosyslogd-1.1.0.dist-info/WHEEL
aiosyslogd-1.1.0.dist-info/entry_points.txt
aiosyslogd-1.1.0.dist-info/licenses/LICENSE
aiosyslogd-1.1.0.dist-info/RECORD
