Metadata-Version: 2.4
Name: aiosyslogd
Version: 1.1.0
Summary: Asynchronous Syslog server using asyncio, with an optional uvloop integration and SQLite backend.
License: MIT
License-File: LICENSE
Author: Chaiwat Suttipongsakul
Author-email: cwt@bashell.com
Requires-Python: >=3.11,<4.0
Classifier: License :: OSI Approved :: MIT License
Classifier: Programming Language :: Python :: 3
Classifier: Programming Language :: Python :: 3.11
Classifier: Programming Language :: Python :: 3.12
Classifier: Programming Language :: Python :: 3.13
Classifier: Programming Language :: Python :: 3.14
Provides-Extra: speed
Requires-Dist: aiosqlite (>=0.21.0)
Requires-Dist: loguru (>=0.7.2)
Requires-Dist: meilisearch-python-sdk (>=4.7.0)
Requires-Dist: quart (>=0.20.0)
Requires-Dist: toml (>=0.10.2)
Requires-Dist: uvloop (>=0.21.0,<0.22.0) ; (sys_platform != "win32") and (extra == "speed")
Requires-Dist: winloop (>=0.1.8,<0.2.0) ; (sys_platform == "win32") and (extra == "speed")
Project-URL: GitHub Mirror, https://github.com/cwt/aiosyslogd
Project-URL: Homepage, https://sr.ht/~cwt/aiosyslogd/
Project-URL: Repository, https://hg.sr.ht/~cwt/aiosyslogd
